raga_canvas_cli/__init__.py
raga_canvas_cli/main.py
raga_canvas_cli/commands/__init__.py
raga_canvas_cli/commands/add.py
raga_canvas_cli/commands/certificate.py
raga_canvas_cli/commands/deploy.py
raga_canvas_cli/commands/help.py
raga_canvas_cli/commands/init.py
raga_canvas_cli/commands/list.py
raga_canvas_cli/commands/login.py
raga_canvas_cli/commands/pull.py
raga_canvas_cli/commands/push.py
raga_canvas_cli/commands/set.py
raga_canvas_cli/models/__init__.py
raga_canvas_cli/models/agent.py
raga_canvas_cli/operations/__init__.py
raga_canvas_cli/operations/deploy_agent.py
raga_canvas_cli/operations/get_certificate.py
raga_canvas_cli/operations/help.py
raga_canvas_cli/operations/pull_agent.py
raga_canvas_cli/operations/pull_project.py
raga_canvas_cli/operations/pull_resources.py
raga_canvas_cli/operations/push_agent.py
raga_canvas_cli/operations/update_certificate.py
raga_canvas_cli/services/__init__.py
raga_canvas_cli/services/api_client.py
raga_canvas_cli/utils/__init__.py
raga_canvas_cli/utils/config.py
raga_canvas_cli/utils/exceptions.py
raga_canvas_cli/utils/helpers.py
raga_canvas_cli-1.0.5.dist-info/licenses/LICENSE
raga_canvas_cli-1.0.5.dist-info/METADATA
raga_canvas_cli-1.0.5.dist-info/WHEEL
raga_canvas_cli-1.0.5.dist-info/entry_points.txt
raga_canvas_cli-1.0.5.dist-info/top_level.txt
raga_canvas_cli-1.0.5.dist-info/RECORD
