Metadata-Version: 2.4
Name: raga-canvas-cli
Version: 1.0.5
Summary: CLI tool for interacting with Raga Canvas no-code agent deployment platform
Author-email: Raga AI <support@raga.ai>
License: MIT
Project-URL: Homepage, https://github.com/raga-ai/raga-canvas-cli
Project-URL: Documentation, https://docs.raga.ai/canvas-cli
Project-URL: Repository, https://github.com/raga-ai/raga-canvas-cli
Project-URL: Issues, https://github.com/raga-ai/raga-canvas-cli/issues
Keywords: cli,agent,deployment,no-code,ai
Classifier: Development Status :: 4 - Beta
Classifier: Intended Audience :: Developers
Classifier: License :: OSI Approved :: MIT License
Classifier: Operating System :: OS Independent
Classifier: Programming Language :: Python :: 3
Classifier: Programming Language :: Python :: 3.8
Classifier: Programming Language :: Python :: 3.9
Classifier: Programming Language :: Python :: 3.10
Classifier: Programming Language :: Python :: 3.11
Classifier: Programming Language :: Python :: 3.12
Requires-Python: >=3.8
License-File: LICENSE
Requires-Dist: click>=8.0.0
Requires-Dist: requests>=2.25.0
Requires-Dist: pyyaml>=6.0
Requires-Dist: rich>=12.0.0
Requires-Dist: keyring>=23.0.0
Requires-Dist: python-dotenv>=0.19.0
Requires-Dist: pydantic>=1.8.0
Requires-Dist: tabulate>=0.9.0
Requires-Dist: pathlib
Requires-Dist: typing-extensions>=4.0.0
Provides-Extra: dev
Requires-Dist: pytest>=7.0.0; extra == "dev"
Requires-Dist: pytest-cov>=4.0.0; extra == "dev"
Requires-Dist: black>=22.0.0; extra == "dev"
Requires-Dist: flake8>=5.0.0; extra == "dev"
Requires-Dist: mypy>=0.991; extra == "dev"
Requires-Dist: pre-commit>=2.20.0; extra == "dev"
Dynamic: license-file
